gdmo/__init__.py
gdmo/api/__init__.py
gdmo/api/apirequest.py
gdmo/dbx/__init__.py
gdmo/dbx/dbxclearcachedtables.py
gdmo/dbx/dbxemail.py
gdmo/dbx/dbxmassemail.py
gdmo/dbx/dbxwidget.py
gdmo/forecasting/__init__.py
gdmo/forecasting/timeseriesforecast.py
gdmo/tables/__init__.py
gdmo/tables/delta.py
gdmo/tables/gold.py
gdmo/tables/landing.py
gdmo-1.0.27.dist-info/licenses/LICENSE
gdmo-1.0.27.dist-info/METADATA
gdmo-1.0.27.dist-info/WHEEL
gdmo-1.0.27.dist-info/top_level.txt
gdmo-1.0.27.dist-info/RECORD
