Metadata-Version: 2.4
Name: gdmo
Version: 1.0.27
Summary: GDMO native classes for standardized interaction with data objects within Azure Databricks. Contains TimeSeriesForecasting, APIRequest, Landing, Delta, GoldConsolidation, and DBx functions.
Author: Stephan Kuiper, Taylor Fialkowski
License-Expression: Apache-2.0
Project-URL: Homepage, https://github.com/
Project-URL: Changelog, https://github.com/
Project-URL: Issues, https://github.com/
Project-URL: CI, https://github.com/
Classifier: Development Status :: 4 - Beta
Requires-Python: >=3.8
License-File: LICENSE
Requires-Dist: openpyxl
Requires-Dist: fsspec
Requires-Dist: adal
Requires-Dist: pandas
Requires-Dist: numpy
Requires-Dist: matplotlib
Requires-Dist: ipython
Requires-Dist: statsmodels
Requires-Dist: prophet
Requires-Dist: scipy
Requires-Dist: pyspark
Requires-Dist: delta-spark
Requires-Dist: requests
Requires-Dist: Office365-REST-Python-Client
Provides-Extra: test
Requires-Dist: pytest; extra == "test"
Requires-Dist: pytest-mock; extra == "test"
Requires-Dist: prophet; extra == "test"
Requires-Dist: adal; extra == "test"
Dynamic: license-file
